controllable/__main__.py
controllable/app.py
controllable/landmarkers.py
controllable/mouse_interpolator.py
controllable/video_feed.py
controllable_py-0.1.2.dist-info/licenses/LICENSE
controllable_py-0.1.2.dist-info/METADATA
controllable_py-0.1.2.dist-info/WHEEL
controllable_py-0.1.2.dist-info/entry_points.txt
controllable_py-0.1.2.dist-info/top_level.txt
controllable_py-0.1.2.dist-info/RECORD
